MANIFEST.in
README.md
setup.py
servicenow.egg-info/PKG-INFO
servicenow.egg-info/SOURCES.txt
servicenow.egg-info/dependency_links.txt
servicenow.egg-info/requires.txt
servicenow.egg-info/top_level.txt
src/servicenow/Connection.py
src/servicenow/ServiceNow.py
src/servicenow/Utils.py
src/servicenow/__init__.py
src/servicenow/drivers/SOAP.py
src/servicenow/drivers/__init__.py