Metadata-Version: 1.0
Name: servicenow
Version: 2.0.1
Summary: Python Library to interact with and manage the ServiceNow database
Home-page: https://github.com/locaweb/python-servicenow
Author: Francisco Freire
Author-email: francisco.freire@locaweb.com.br
License: Apache
Platform: UNKNOWN
